routeros_prometheus_client/__init__.py
routeros_prometheus_client/__main__.py
RouterOS_Prometheus_client-0.0.1.dist-info/LICENSE
RouterOS_Prometheus_client-0.0.1.dist-info/METADATA
RouterOS_Prometheus_client-0.0.1.dist-info/WHEEL
RouterOS_Prometheus_client-0.0.1.dist-info/entry_points.txt
RouterOS_Prometheus_client-0.0.1.dist-info/top_level.txt
RouterOS_Prometheus_client-0.0.1.dist-info/RECORD
