Metadata-Version: 2.1
Name: RouterOS-Prometheus-client
Version: 0.0.1
Summary: Python Prometheus client to RouterBoard devices produced by MikroTik.
Home-page: https://github.com/vanche93/RouterOS-Prometheus-client
Author: Ivan Burashev
Author-email: vanche93@yandex.ru
License: MIT
Platform: UNKNOWN
Classifier: Programming Language :: Python
Classifier: Programming Language :: Python :: 3.6
Classifier: Programming Language :: Python :: 3.7
Classifier: License :: OSI Approved :: MIT License
Requires-Python: >=3.6
Requires-Dist: RouterOS-api
Requires-Dist: prometheus-client
